marci/__init__.py
marci/_version.py
marci/budgets.py
marci/campaigns.py
marci/core.py
marci/portfolio.py
marci/simulated_data.py
marci/utils/__init__.py
marci/utils/conversion_delay.py
marci/utils/distributions.py
marci/utils/elasticity.py
marci/utils/math_utils.py
marci/utils/performance_stats.py
marci/utils/plot_utils.py
marci/utils/seasonality.py
marci-0.2.3.dist-info/METADATA
marci-0.2.3.dist-info/WHEEL
marci-0.2.3.dist-info/top_level.txt
marci-0.2.3.dist-info/RECORD
