Metadata-Version: 2.4
Name: marci
Version: 0.2.3
Summary: Marci: Marketing Science utilities for campaign analysis and simulation
Author-email: Marci Contributors <noallynoclan@gmail.com>
Project-URL: Homepage, https://github.com/noallynoclan/marci
Project-URL: Repository, https://github.com/noallynoclan/marci
Project-URL: Issues, https://github.com/noallynoclan/marci/issues
Keywords: marketing,analytics,campaign,simulation,elasticity,seasonality
Classifier: Programming Language :: Python :: 3
Classifier: Programming Language :: Python :: 3 :: Only
Classifier: Programming Language :: Python :: 3.8
Classifier: Programming Language :: Python :: 3.9
Classifier: Programming Language :: Python :: 3.10
Classifier: Programming Language :: Python :: 3.11
Classifier: Programming Language :: Python :: 3.12
Classifier: Operating System :: OS Independent
Requires-Python: >=3.8
Requires-Dist: numpy>=1.24
Requires-Dist: pandas>=2.0
Requires-Dist: matplotlib>=3.5
Requires-Dist: seaborn>=0.11
Requires-Dist: scipy>=1.10
Provides-Extra: dev
Requires-Dist: pytest>=7.0; extra == "dev"
Requires-Dist: pytest-cov>=4.0; extra == "dev"
Requires-Dist: black>=22.0; extra == "dev"
Requires-Dist: flake8>=5.0; extra == "dev"
Requires-Dist: mypy>=1.0; extra == "dev"
